README.md
setup.py
findsubdomains/__init__.py
findsubdomains/cli.py
findsubdomains/core.py
findsubdomains/utils.py
pyfindsubdomains.egg-info/PKG-INFO
pyfindsubdomains.egg-info/SOURCES.txt
pyfindsubdomains.egg-info/dependency_links.txt
pyfindsubdomains.egg-info/entry_points.txt
pyfindsubdomains.egg-info/requires.txt
pyfindsubdomains.egg-info/top_level.txt