Metadata-Version: 1.1
Name: pyfindsubdomains
Version: 0.0.2.3
Summary: This is a python3 wrapper to FindSubDomains
Home-page: https://github.com/Den1al/pyfindsubdomains
Author: @Daniel_Abeles
Author-email: abeles22@gmail.com
License: BSD
Keywords: FindSubDomains,bruteforce,dns,subdomain
Platform: UNKNOWN
Classifier: Programming Language :: Python
Classifier: Programming Language :: Python :: 3.6
Classifier: Environment :: Console
Classifier: Intended Audience :: Developers
Classifier: Intended Audience :: System Administrators
Classifier: License :: OSI Approved :: GNU General Public License v3 (GPLv3)
Classifier: Operating System :: OS Independent
Classifier: Topic :: System :: Monitoring
Classifier: Topic :: System :: Networking
Classifier: Topic :: System :: Networking :: Firewalls
Classifier: Topic :: System :: Networking :: Monitoring
